{
  "paddingSM": {
    "value": 12,
    "type": "number"
  },
  "borderRadius": {
    "value": 8,
    "type": "number"
  },
  "Input": {
    "controlPaddingHorizontal": {
      "value": 12,
      "type": "number"
    },
    "colorBgContainer": {
      "value": "#ffffff",
      "type": "color"
    },
    "colorBorder": {
      "value": "#e3e3e3",
      "type": "color"
    },
    "colorTextPlaceholder": {
      "value": "#00000040",
      "type": "color"
    },
    "colorPrimary": {
      "value": "#4a7cfe",
      "type": "color"
    },
    "colorText": {
      "value": "#000000e0",
      "type": "color"
    },
    "colorError": {
      "value": "#ff4d4f",
      "type": "color"
    }
  },
  "borderRadiusLG": {
    "value": 10,
    "type": "number"
  },
  "DatePicker": {
    "marginXXS": {
      "value": 4,
      "type": "number"
    },
    "controlPaddingHorizontal": {
      "value": 12,
      "type": "number"
    },
    "contorlHeight": {
      "value": 32,
      "type": "number"
    },
    "colorTextDisabled": {
      "value": "#00000040",
      "type": "color"
    },
    "colorBorder": {
      "value": "#e3e3e3",
      "type": "color"
    },
    "colorBgContainer": {
      "value": "#ffffff",
      "type": "color"
    },
    "colorPrimary": {
      "value": "#4a7cfe",
      "type": "color"
    },
    "colorText": {
      "value": "#000000e0",
      "type": "color"
    },
    "colorBgElevated": {
      "value": "#ffffff",
      "type": "color"
    },
    "colorSplit": {
      "value": "#0000000f",
      "type": "color"
    },
    "colorTextDescription": {
      "value": "#00000073",
      "type": "color"
    },
    "colorTextLightSolid": {
      "value": "#ffffff",
      "type": "color"
    }
  },
  "Checkbox": {
    "marginXS": {
      "value": 8,
      "type": "number"
    },
    "colorBorder": {
      "value": "#e3e3e3",
      "type": "color"
    },
    "colorBgContainer": {
      "value": "#ffffff",
      "type": "color"
    },
    "colorWhite": {
      "value": "#ffffff",
      "type": "color"
    },
    "colorPrimary": {
      "value": "#4a7cfe",
      "type": "color"
    },
    "colorText": {
      "value": "#000000e0",
      "type": "color"
    },
    "colorTextDisabled": {
      "value": "#00000040",
      "type": "color"
    }
  },
  "Dropdown": {
    "paddingXXS": {
      "value": 4,
      "type": "number"
    },
    "borderRadiusLG": {
      "value": 10,
      "type": "number"
    },
    "borderRadiusSM": {
      "value": 6,
      "type": "number"
    },
    "controlHeight": {
      "value": 32,
      "type": "number"
    },
    "marginXS": {
      "value": 8,
      "type": "number"
    },
    "controlPaddingHorizontal": {
      "value": 12,
      "type": "number"
    },
    "colorBgElevated": {
      "value": "#ffffff",
      "type": "color"
    },
    "colorText": {
      "value": "#000000e0",
      "type": "color"
    },
    "colorPrimary": {
      "value": "#4a7cfe",
      "type": "color"
    },
    "contrlItemBgActive": {
      "value": "#f0f7ff",
      "type": "color"
    },
    "controlItemBgHover": {
      "value": "#0000000a",
      "type": "color"
    },
    "controlItemBgActive": {
      "value": "#f0f7ff",
      "type": "color"
    },
    "colorError": {
      "value": "#ff4d4f",
      "type": "color"
    }
  },
  "Table": {
    "paddingXS": {
      "value": 8,
      "type": "number"
    },
    "borderRadiusLG": {
      "value": 10,
      "type": "number"
    },
    "colorSplit": {
      "value": "#0000000f",
      "type": "color"
    },
    "colorText": {
      "value": "#000000e0",
      "type": "color"
    },
    "colorTextDisabled": {
      "value": "#00000040",
      "type": "color"
    },
    "colorBgContainer": {
      "value": "#ffffff",
      "type": "color"
    },
    "colorFillAlter": {
      "value": "#00000005",
      "type": "color"
    }
  },
  "Transfer": {
    "controlHeight": {
      "value": 32,
      "type": "number"
    },
    "PaddingSM": {
      "value": 12,
      "type": "number"
    },
    "controlItemBgActive": {
      "value": "#f0f7ff",
      "type": "color"
    },
    "controlItemBgHover": {
      "value": "#0000000a",
      "type": "color"
    }
  },
  "Modal": {
    "borderRadiusLG": {
      "value": 10,
      "type": "number"
    },
    "paddingContentHorizontalLG": {
      "value": 24,
      "type": "number"
    },
    "colorText": {
      "value": "#000000e0",
      "type": "color"
    }
  },
  "colorTextSecondary": {
    "value": "#000000a6",
    "type": "color"
  },
  "colorBgContainer": {
    "value": "#ffffff",
    "type": "color"
  },
  "colorBgSecondary": {
    "value": "#f0f0f0",
    "type": "color"
  },
  "colorFillAlter": {
    "value": "#00000005",
    "type": "color"
  },
  "colorSplit": {
    "value": "#0000000f",
    "type": "color"
  },
  "colorIcon": {
    "value": "#00000073",
    "type": "color"
  },
  "colorTextTertiary": {
    "value": "#00000073",
    "type": "color"
  },
  "colorPrimaryBase": {
    "value": "#4a7cfe",
    "type": "color"
  },
  "Button": {
    "colorPrimary": {
      "value": "#4a7cfe",
      "type": "color"
    },
    "colorPrimaryHover": {
      "value": "#739fff",
      "type": "color"
    },
    "colorPrimaryActive": {
      "value": "#345dd9",
      "type": "color"
    },
    "colorTextLightSolid": {
      "value": "#ffffff",
      "type": "color"
    },
    "colorBorder": {
      "value": "#e3e3e3",
      "type": "color"
    },
    "colorBgContainerDisabled": {
      "value": "#0000000a",
      "type": "color"
    },
    "colorTextDisabled": {
      "value": "#00000040",
      "type": "color"
    },
    "colorBgTextHover": {
      "value": "#0000000f",
      "type": "color"
    }
  },
  "Divider": {
    "colorSplit": {
      "value": "#0000000f",
      "type": "color"
    }
  },
  "Test": {}
}
